llmebench/__init__.py
llmebench/__main__.py
llmebench/asset_utils.py
llmebench/benchmark.py
llmebench/utils.py
llmebench/datasets/ADI.py
llmebench/datasets/ANERcorp.py
llmebench/datasets/ANSFactuality.py
llmebench/datasets/ANSStance.py
llmebench/datasets/ARCD.py
llmebench/datasets/ASND.py
llmebench/datasets/Adult.py
llmebench/datasets/Aqmar.py
llmebench/datasets/ArMemes.py
llmebench/datasets/ArSAS.py
llmebench/datasets/ArSarcasm.py
llmebench/datasets/ArSarcasm2.py
llmebench/datasets/AraBench.py
llmebench/datasets/ArabGend.py
llmebench/datasets/ArapTweet.py
llmebench/datasets/BanFakeNews.py
llmebench/datasets/BanglaNewsCategorization.py
llmebench/datasets/BanglaSentiment.py
llmebench/datasets/BanglaVITD.py
llmebench/datasets/BibleMaghrebiDiacritization.py
llmebench/datasets/COVID19Factuality.py
llmebench/datasets/CSV.py
llmebench/datasets/CT22Attentionworthy.py
llmebench/datasets/CT22Checkworthiness.py
llmebench/datasets/CT22Claim.py
llmebench/datasets/CT22Harmful.py
llmebench/datasets/CT23Subjectivity.py
llmebench/datasets/Emotion.py
llmebench/datasets/HuggingFace.py
llmebench/datasets/JSONL.py
llmebench/datasets/Location.py
llmebench/datasets/MGBWords.py
llmebench/datasets/MLQA.py
llmebench/datasets/MultiNativQA.py
llmebench/datasets/NameInfo.py
llmebench/datasets/OSACT4SubtaskA.py
llmebench/datasets/OSACT4SubtaskB.py
llmebench/datasets/PADT.py
llmebench/datasets/QADI.py
llmebench/datasets/QCRIDialectalArabicPOS.py
llmebench/datasets/QCRIDialectalArabicSegmentation.py
llmebench/datasets/SANADAkhbarona.py
llmebench/datasets/SANADAlArabiya.py
llmebench/datasets/SANADAlKhaleej.py
llmebench/datasets/SQuADBase.py
llmebench/datasets/STSQ2Q.py
llmebench/datasets/SemEval17T1STS.py
llmebench/datasets/SemEval17T2STS.py
llmebench/datasets/SemEval23T3Propaganda.py
llmebench/datasets/Spam.py
llmebench/datasets/TSV.py
llmebench/datasets/ThatiAR.py
llmebench/datasets/TyDiQA.py
llmebench/datasets/UnifiedFCFactuality.py
llmebench/datasets/UnifiedFCStance.py
llmebench-1.1.0.dist-info/METADATA
llmebench-1.1.0.dist-info/WHEEL
llmebench-1.1.0.dist-info/top_level.txt
llmebench-1.1.0.dist-info/RECORD
