Metadata-Version: 2.2
Name: llmebench
Version: 1.1.0
Summary: A Flexible Framework for Accelerating LLMs Benchmarking
Home-page: https://llmebench.qcri.org
Author: Fahim Dalvi
Author-email: faimaduddin@hbku.edu.qa
Project-URL: Documentation, https://github.com/qcri/LLMeBench
Project-URL: Bug Tracker, https://github.com/qcri/LLMeBench
Classifier: Programming Language :: Python :: 3
Classifier: License :: OSI Approved :: BSD License
Classifier: Operating System :: OS Independent
Requires-Python: >=3.8
Requires-Dist: datasets==2.14.6
Requires-Dist: nltk==3.8.1
Requires-Dist: openai==1.59.7
Requires-Dist: anthropic==0.43.0
Requires-Dist: pandas==2.0.2
Requires-Dist: pooch==1.7.0
Requires-Dist: python-dotenv==1.0.0
Requires-Dist: scikit-learn==1.2.2
Requires-Dist: tenacity==8.2.2
Requires-Dist: websockets==11.0.3
Requires-Dist: evaluate==0.4.2
Requires-Dist: rouge-score==0.1.2
Requires-Dist: absl-py==2.1.0
Requires-Dist: GitPython==3.1.43
Requires-Dist: numpy<2
Provides-Extra: dev
Requires-Dist: langcodes==3.3.0; extra == "dev"
Requires-Dist: pytest==7.3.1; extra == "dev"
Requires-Dist: pytest-cov==4.1.0; extra == "dev"
Requires-Dist: pytest-subtests==0.11.0; extra == "dev"
Requires-Dist: ufmt==1.3.2; extra == "dev"
Provides-Extra: fewshot
Requires-Dist: langchain==0.0.198; extra == "fewshot"
Requires-Dist: sentence_transformers==3.2.1; extra == "fewshot"
Requires-Dist: faiss-cpu==1.8.0; extra == "fewshot"
